itk_simpleitkfilters.libs/libtbb-f489fd38.so.12.9
itk_simpleitkfilters-1.0.0.dist-info/LICENSE
itk_simpleitkfilters-1.0.0.dist-info/WHEEL
itk_simpleitkfilters-1.0.0.dist-info/top_level.txt
itk_simpleitkfilters-1.0.0.dist-info/RECORD
itk_simpleitkfilters-1.0.0.dist-info/METADATA
itk/itkHessianImageFilterPython.py
itk/itkDICOMOrientImageFilterPython.py
itk/itkDICOMOrientationPython.py
itk/_SimpleITKFiltersPython.abi3.so
itk/SimpleITKFiltersPython.py
itk/itkNPasteImageFilterPython.py
itk/itkObjectnessImageFilterPython.py
itk/Configuration/SimpleITKFiltersConfig.py
itk/Configuration/SimpleITKFilters_snake_case.py
